README.md
setup.cfg
setup.py
openrec/__init__.py
openrec.egg-info/PKG-INFO
openrec.egg-info/SOURCES.txt
openrec.egg-info/dependency_links.txt
openrec.egg-info/requires.txt
openrec.egg-info/top_level.txt
openrec/tf1/__init__.py
openrec/tf1/fast_dot_product_server.py
openrec/tf1/model_trainer.py
openrec/tf1/legacy/__init__.py
openrec/tf1/legacy/implicit_model_trainer.py
openrec/tf1/legacy/itr_mlp_model_trainer.py
openrec/tf1/legacy/modules/__init__.py
openrec/tf1/legacy/modules/module.py
openrec/tf1/legacy/modules/extractions/__init__.py
openrec/tf1/legacy/modules/extractions/extraction.py
openrec/tf1/legacy/modules/extractions/identity_mapping.py
openrec/tf1/legacy/modules/extractions/latent_factor.py
openrec/tf1/legacy/modules/extractions/look_up.py
openrec/tf1/legacy/modules/extractions/multi_layer_fc.py
openrec/tf1/legacy/modules/extractions/sdae.py
openrec/tf1/legacy/modules/extractions/temporal_latent_factor.py
openrec/tf1/legacy/modules/fusions/__init__.py
openrec/tf1/legacy/modules/fusions/average.py
openrec/tf1/legacy/modules/fusions/concat.py
openrec/tf1/legacy/modules/fusions/fusion.py
openrec/tf1/legacy/modules/interactions/__init__.py
openrec/tf1/legacy/modules/interactions/interaction.py
openrec/tf1/legacy/modules/interactions/ns_eu_dist.py
openrec/tf1/legacy/modules/interactions/ns_log.py
openrec/tf1/legacy/modules/interactions/pairwise_eu_dist.py
openrec/tf1/legacy/modules/interactions/pairwise_hinge.py
openrec/tf1/legacy/modules/interactions/pairwise_log.py
openrec/tf1/legacy/modules/interactions/pointwise_ge_ce.py
openrec/tf1/legacy/modules/interactions/pointwise_ge_mlp_ce.py
openrec/tf1/legacy/modules/interactions/pointwise_mlp_ce.py
openrec/tf1/legacy/modules/interactions/pointwise_mse.py
openrec/tf1/legacy/recommenders/__init__.py
openrec/tf1/legacy/recommenders/bpr.py
openrec/tf1/legacy/recommenders/cdl.py
openrec/tf1/legacy/recommenders/cml.py
openrec/tf1/legacy/recommenders/concat_visual_bpr.py
openrec/tf1/legacy/recommenders/gmf.py
openrec/tf1/legacy/recommenders/itr_mlp.py
openrec/tf1/legacy/recommenders/nbpr.py
openrec/tf1/legacy/recommenders/pmf.py
